omp/__init__.py
omp/clauses/__init__.py
omp/clauses/nowait.py
omp/clauses/private.py
omp/clauses/reduction.py
omp/clauses/schedule.py
omp/core/__init__.py
omp/core/ast_tools.py
omp/core/entry.py
omp/core/openmp.py
omp/core/primitives.py
omp/core/threading.py
omp/directives/__init__.py
omp/directives/barrier_directive.py
omp/directives/critical_construct.py
omp/directives/for_construct.py
omp/directives/parallel_construct.py
omp/directives/parallel_for_construct.py
omp/directives/single_construct.py
openmpy-0.1.0.dist-info/LICENSE.md
openmpy-0.1.0.dist-info/METADATA
openmpy-0.1.0.dist-info/WHEEL
openmpy-0.1.0.dist-info/RECORD
