Metadata-Version: 2.3
Name: openmpy
Version: 0.1.0
Summary: A native implementation of OpenMP in Python.
Author: Dorian OUAKLI
Author-email: dorian.ouakli@xwiki.com
Requires-Python: >=3.9,<4.0
Classifier: Programming Language :: Python :: 3
Classifier: Programming Language :: Python :: 3.9
Classifier: Programming Language :: Python :: 3.10
Classifier: Programming Language :: Python :: 3.11
Classifier: Programming Language :: Python :: 3.12
Classifier: Programming Language :: Python :: 3.13
